xwordlist/__init__.py
xwordlist/xwl.py
xwordlist/xwlconfig.py
xwordlist/xwordlist.py
xwordlist-23.0.2.dist-info/entry_points.txt
xwordlist-23.0.2.dist-info/LICENSE
xwordlist-23.0.2.dist-info/WHEEL
xwordlist-23.0.2.dist-info/METADATA
xwordlist-23.0.2.dist-info/RECORD
