Metadata-Version: 2.1
Name: xwordlist
Version: 23.0.2
Summary: Software to help create, build and organize crossword puzzle word lists
Home-page: https://xwl.ist
License: MIT
Author: Andrew Anker
Author-email: aa@quid.pro
Requires-Python: >=3.9,<4.0
Classifier: Development Status :: 5 - Production/Stable
Classifier: Intended Audience :: End Users/Desktop
Classifier: License :: OSI Approved :: MIT License
Classifier: Programming Language :: Python
Classifier: Programming Language :: Python :: 3
Classifier: Programming Language :: Python :: 3.9
Classifier: Programming Language :: Python :: 3.10
Classifier: Programming Language :: Python :: 3.11
Classifier: Programming Language :: Python :: 3
Classifier: Programming Language :: Python :: 3.9
Classifier: Topic :: Games/Entertainment :: Puzzle Games
Requires-Dist: anyascii (>=0.3.1,<0.4.0)
Requires-Dist: beautifulsoup4 (>=4.11.1,<5.0.0)
Requires-Dist: prompt-toolkit (>=3.0.20,<4.0.0)
Requires-Dist: requests (>=2.28.1,<3.0.0)
Project-URL: Documentation, https://xwl.ist/help/
Project-URL: Repository, https://github.com/aanker/xwordlist
